<?xml version="1.0" encoding="UTF-8"?>
<persistence version="2.2" xmlns="http://xmlns.jcp.org/xml/ns/persistence" xmlns:xsi="http://www.w3.org/2001/XMLSchema-instance" xsi:schemaLocation="http://xmlns.jcp.org/xml/ns/persistence http://xmlns.jcp.org/xml/ns/persistence/persistence_2_2.xsd">
	<persistence-unit name="OnCuoiKy_OGM_Lan2">
	<provider>org.hibernate.ogm.jpa.HibernateOgmPersistence</provider>
	<class>entity.Employee</class>
	<class>entity.Department</class>
	<class>entity.Proposal</class>
		<properties>
			<property name="hibernate.ogm.datastore.provider"
				value="mongodb" />
			<property name="hibernate.ogm.datastore.host"
				value="localhost" />
			<property name="hibernate.ogm.datastore.port" value="27017" />
			<property name="hibernate.ogm.datastore.database"
				value="onCuoiKyOGMLan1" />
			<property name="hibernate.ogm.datastore.create_database"
				value="true" />
		</properties>
	</persistence-unit>
</persistence>
